Workbook
Name FO_AR_Benne_Contener_WC: 'Base FO'!$B$172
Name FO_AR_Pelle: 'Base FO'!$B$173
Name FO_Abattement_Pelle_Gros_Chantier: 'Base FO'!$B$174
Name FO_Adoucisseur_15: 'Base FO'!$B$175
Name FO_Adoucisseur_5: 'Base FO'!$B$176
Name FO_Amene_Repli_Equipe: 'Base FO'!$B$177
Name FO_Boitier_Plexo: 'Base FO'!$B$178
Name FO_Boulet_Compresseur_Type_1: 'Base FO'!$B$179
Name FO_Boulet_Compresseur_Type_2: 'Base FO'!$B$180
Name FO_Boulet_Compresseur_Type_3: 'Base FO'!$B$181
Name FO_Boulet_Duree_Location_Compresseur: 'Base FO'!$B$182
Name FO_Boulet_Duree_Location_Pelle: 'Base FO'!$B$183
Name FO_Boulet_Location_Pelle_h: 'Base FO'!$B$184
Name FO_Boulet_MO_AR_Compresseur_Pers: 'Base FO'!$B$185
Name FO_Boulet_MO_AR_Compresseur_h: 'Base FO'!$B$186
Name FO_Boulet_MO_Extremites_Pers: 'Base FO'!$B$187
Name FO_Boulet_MO_Extremites_h: 'Base FO'!$B$188
Name FO_Boulet_MO_Piston_Pers: 'Base FO'!$B$189
Name FO_Boulet_MO_Piston_h: 'Base FO'!$B$190
Name FO_Boulet_MO_Poussee_Pers: 'Base FO'!$B$191
Name FO_Boulet_MO_Poussee_h: 'Base FO'!$B$192
Name FO_Boulet_MO_Retrait_Pers: 'Base FO'!$B$193
Name FO_Boulet_MO_Retrait_h: 'Base FO'!$B$194
Name FO_Boulet_Nb_Bobines: 'Base FO'!$B$195
Name FO_Boulet_Nb_Boulets: 'Base FO'!$B$196
Name FO_Boulet_Nb_Fonds_Bombes: 'Base FO'!$B$197
Name FO_Boulet_Nb_Tetes_Chat: 'Base FO'!$B$198
Name FO_Boulet_Nb_Vannes_BS_PR: 'Base FO'!$B$199
Name FO_Boulet_Prix_Tete_Chat: 'Base FO'!$B$200
Name FO_Calo_Nb_Pers_Deplacement: 'Base FO'!$B$201
Name FO_Camion_Plateau: 'Base FO'!$B$202
Name FO_Conservation_Circulation: 'Base FO'!$B$203
Name FO_Conservation_Dechets: 'Base FO'!$B$204
Name FO_Conservation_Dosage: 'Base FO'!$B$205
Name FO_Conservation_Produit: 'Base FO'!$B$206
Name FO_Conservation_Remplissage: 'Base FO'!$B$207
Name FO_Conservation_Vidange: 'Base FO'!$B$208
Name FO_Cout_Journee_Benne: 'Base FO'!$B$209
Name FO_Cout_Journee_Contener: 'Base FO'!$B$210
Name FO_Cout_Journee_Pelle: 'Base FO'!$B$211
Name FO_Cout_Journee_WC: 'Base FO'!$B$212
Name FO_DN_Accessoires_Injection: 'Base FO'!$B$213
Name FO_Dechets_DIB_Tonne: 'Base FO'!$B$214
Name FO_Depose_Arrondi_Prix_MO: 'Base FO'!$B$215
Name FO_Depose_Espacement_Coupes: 'Base FO'!$B$216
Name FO_Depose_Volume_Rotation: 'Base FO'!$B$217
Name FO_EauAdoucie_Eau_m3: 'Base FO'!$B$218
Name FO_EauAdoucie_Flexible: 'Base FO'!$B$219
Name FO_EauAdoucie_Mise_En_Service: 'Base FO'!$B$220
Name FO_EauAdoucie_Sel: 'Base FO'!$B$221
Name FO_EauAdoucie_Soude: 'Base FO'!$B$222
Name FO_Epreuve_Debit_Poteau: 'Base FO'!$B$223
Name FO_Epreuve_Eau_m3: 'Base FO'!$B$224
Name FO_Epreuve_Hydrocureur_h: 'Base FO'!$B$225
Name FO_Epreuve_MO_Decompression: 'Base FO'!$B$226
Name FO_Epreuve_MO_Montee_Pression: 'Base FO'!$B$227
Name FO_Epreuve_Mise_En_Place: 'Base FO'!$B$228
Name FO_Epreuve_Plafond_Duree: 'Base FO'!$B$229
Name FO_Epreuve_Pompe: 'Base FO'!$B$230
Name FO_Epreuve_Rapport: 'Base FO'!$B$231

Sheet Base MO
A1: BASE MAIN D'ŒUVRE (MAQUETTE DE TEST — PRIX FICTIFS)
A3: TAUX HORAIRES PAR POSTE | F3: PARAMÈTRES GÉNÉRAUX
A4: Poste | B4: Taux SCR | C4: FG Chantier | D4: FG Structure | E4: Sinistre | F4: Total /h | G4: Heures /jour | H4: Total /jour
A5: Soudeur | B5: 70 | C5: 5 | D5: 20 | E5: 5 | F5: 100 | G5: 10 | H5: 1000
A6: Tuyauteur | B6: 60 | C6: 5 | D6: 20 | E6: 5 | F6: 90 | G6: 10 | H6: 900
A7: Manchonneur | B7: 50 | C7: 5 | D7: 20 | E7: 5 | F7: 80 | G7: 10 | H7: 800
A8: Chauffeur d'engin | B8: 55 | C8: 5 | D8: 20 | E8: 5 | F8: 85 | G8: 10 | H8: 850
A9: Opérations Spécifiques (OS) | B9: 70 | C9: 5 | D9: 20 | E9: 5 | F9: 100 | G9: 10 | H9: 1000
A11: COMPOSITION ÉQUIPES TYPE
A12: Équipe | B12: Soudeur | C12: Tuyauteur | D12: Manchonneur | E12: Chauffeur | F12: Nb pers | G12: Coût /jour | H12: Coût /h
A13: Soudeur (S) | B13: 1 | C13: 0 | D13: 0 | E13: 0 | F13: 1 | G13: 1000 | H13: 100
A14: Soudeur + Tuyauteur (S+T) | B14: 1 | C14: 1 | D14: 0 | E14: 0 | F14: 2 | G14: 1900 | H14: 190
A15: Soudeur + Tuyauteur + Chauffeur (S+T+P) | B15: 1 | C15: 1 | D15: 0 | E15: 1 | F15: 3 | G15: 2750 | H15: 275
A16: Manchonneur (M) | B16: 0 | C16: 0 | D16: 1 | E16: 0 | F16: 1 | G16: 800 | H16: 80
A17: Manchonneurs x 2 (M +M) | B17: 0 | C17: 0 | D17: 2 | E17: 0 | F17: 2 | G17: 1600 | H17: 160
A18: Opérations Spécifiques (OS) | B18: 0 | C18: 0 | D18: 0 | E18: 0 | F18: 1 | G18: 1000 | H18: 100
A19: OS x 2 | B19: 0 | C19: 0 | D19: 0 | E19: 0 | F19: 2 | G19: 2000 | H19: 200
A20: OS x 3 | B20: 0 | C20: 0 | D20: 0 | E20: 0 | F20: 3 | G20: 3000 | H20: 300
A22: CADENCES & COÛTS MO PAR SOUDURE / ML
A23: DN | B23: Pouce | C23: Cadence/jour 1 soudeur | D23: Cadence/jour Soud+Tuy | E23: Cadence/jour Soud+Tuy+Chauff | F23: MO / soudure 1 soudeur | G23: MO / soudure Soud+Tuy | H23: MO / soudure Soud+Tuy+Chauff | I23: Cadence/jour 2 manchonneurs | J23: Cadence/jour 1 manchonneur | K23: Cadence/jour 2 manchonneurs | L23: Cadence/jour 1 manchonneur | M23: Cadence/jour 2 manchonneurs | N23: Cadence/jour 1 manchonneur | O23: Cadence/jour 2 manchonneurs | P23: Cadence/jour 1 manchonneur | Q23: Cadence/jour 2 manchonneurs | R23: Cadence/jour 1 manchonneur | S23: Cadence/jour 2 manchonneurs | T23: Cadence/jour 1 manchonneur | U23: Dépression min / manchon | V23: Fils DH min / manchon | W23: Ressuage min / manchon | X23: Itopo min / manchon | Y23: Pression min / manchon | Z23: Pose coussin min / coussin
A24: 20 | B24: 1 | C24: 20 | D24: 40 | E24: 40 | F24: 50 | G24: 47.5 | H24: 68.75 | I24: 40 | J24: 20 | K24: 40 | L24: 20 | M24: 40 | N24: 20 | O24: 38 | P24: 19 | Q24: 38 | R24: 19 | S24: 38 | T24: 19 | U24: 5 | V24: 3 | W24: 2 | X24: 2 | Y24: 3 | Z24: 2
A25: 25 | B25: 1 | C25: 20 | D25: 40 | E25: 40 | F25: 50 | G25: 47.5 | H25: 68.75 | I25: 40 | J25: 20 | K25: 40 | L25: 20 | M25: 40 | N25: 20 | O25: 38 | P25: 19 | Q25: 38 | R25: 19 | S25: 38 | T25: 19 | U25: 5 | V25: 3 | W25: 2 | X25: 2 | Y25: 3
A26: 32 | B26: 1.25 | C26: 16 | D26: 32 | E26: 32 | F26: 62.5 | G26: 59.375 | H26: 85.9375 | I26: 32 | J26: 16 | K26: 32 | L26: 16 | M26: 32 | N26: 16 | O26: 30 | P26: 15 | Q26: 30 | R26: 15 | S26: 30 | T26: 15 | U26: 5 | V26: 3 | W26: 2 | X26: 2 | Y26: 3
A27: 40 | B27: 1.5 | C27: 13 | D27: 27 | E27: 27 | F27: 76.923077 | G27: 70.37037 | H27: 101.85185 | I27: 27 | J27: 13 | K27: 27 | L27: 13 | M27: 27 | N27: 13 | O27: 25 | P27: 12 | Q27: 25 | R27: 12 | S27: 25 | T27: 12 | U27: 5 | V27: 3 | W27: 2 | X27: 2 | Y27: 3
A28: 50 | B28: 2 | C28: 10 | D28: 20 | E28: 20 | F28: 100 | G28: 95 | H28: 137.5 | I28: 20 | J28: 10 | K28: 20 | L28: 10 | M28: 20 | N28: 10 | O28: 18 | P28: 9 | Q28: 18 | R28: 9 | S28: 18 | T28: 9 | U28: 5 | V28: 3 | W28: 2 | X28: 2 | Y28: 3
A29: 65 | B29: 2.5 | C29: 8 | D29: 16 | E29: 16 | F29: 125 | G29: 118.75 | H29: 171.875 | I29: 16 | J29: 8 | K29: 16 | L29: 8 | M29: 16 | N29: 8 | O29: 14 | P29: 7 | Q29: 14 | R29: 7 | S29: 14 | T29: 7 | U29: 5 | V29: 3 | W29: 2 | X29: 2 | Y29: 3
A30: 80 | B30: 3 | C30: 7 | D30: 13 | E30: 13 | F30: 142.85714 | G30: 146.15385 | H30: 211.53846 | I30: 13 | J30: 7 | K30: 13 | L30: 7 | M30: 13 | N30: 7 | O30: 11 | P30: 6 | Q30: 11 | R30: 6 | S30: 11 | T30: 6 | U30: 5 | V30: 3 | W30: 2 | X30: 2 | Y30: 3
A31: 100 | B31: 4 | C31: 5 | D31: 10 | E31: 10 | F31: 200 | G31: 190 | H31: 275 | I31: 10 | J31: 5 | K31: 10 | L31: 5 | M31: 10 | N31: 5 | O31: 8 | P31: 4 | Q31: 8 | R31: 4 | S31: 8 | T31: 4 | U31: 5 | V31: 3 | W31: 2 | X31: 2 | Y31: 3
A32: 125 | B32: 5 | C32: 4 | D32: 8 | E32: 8 | F32: 250 | G32: 237.5 | H32: 343.75 | I32: 8 | J32: 4 | K32: 8 | L32: 4 | M32: 8 | N32: 4 | O32: 6 | P32: 3 | Q32: 6 | R32: 3 | S32: 6 | T32: 3 | U32: 5 | V32: 3 | W32: 2 | X32: 2 | Y32: 3
A33: 150 | B33: 6 | C33: 3 | D33: 7 | E33: 7 | F33: 333.33333 | G33: 271.42857 | H33: 392.85714 | I33: 7 | J33: 3 | K33: 7 | L33: 3 | M33: 7 | N33: 3 | O33: 5 | P33: 2 | Q33: 5 | R33: 2 | S33: 5 | T33: 2 | U33: 5 | V33: 3 | W33: 2 | X33: 2 | Y33: 3
A34: 200 | B34: 8 | C34: 2 | D34: 5 | E34: 5 | F34: 500 | G34: 380 | H34: 550 | I34: 5 | J34: 2 | K34: 5 | L34: 2 | M34: 5 | N34: 2 | O34: 3 | P34: 1 | Q34: 3 | R34: 1 | S34: 3 | T34: 1 | U34: 5 | V34: 3 | W34: 2 | X34: 2 | Y34: 3
A35: 250 | B35: 10 | C35: 2 | D35: 4 | E35: 4 | F35: 500 | G35: 475 | H35: 687.5 | I35: 4 | J35: 2 | K35: 4 | L35: 2 | M35: 4 | N35: 2 | O35: 2 | P35: 1 | Q35: 2 | R35: 1 | S35: 2 | T35: 1 | U35: 5 | V35: 3 | W35: 2 | X35: 2 | Y35: 3
A36: 300 | B36: 12 | C36: 2 | D36: 3 | E36: 3 | F36: 500 | G36: 633.33333 | H36: 916.66667 | I36: 3 | J36: 2 | K36: 3 | L36: 2 | M36: 3 | N36: 2 | O36: 1 | P36: 1 | Q36: 1 | R36: 1 | S36: 1 | T36: 1 | U36: 5 | V36: 3 | W36: 2 | X36: 2 | Y36: 3
... A41: 600 | B41: 24 | C41: 1 | D41: 2 | E41: 2 | F41: 1000 | G41: 950 | H41: 1375 | I41: 2 | J41: 1 | K41: 2 | L41: 1 | M41: 2 | N41: 1 | O41: 1 | P41: 1 | Q41: 1 | R41: 1 | S41: 1 | T41: 1 | U41: 5 | V41: 3 | W41: 2 | X41: 2 | Y41: 3
A43: TRAVAUX DE NUIT — Surcoût par poste
A62: MO DOE / DOCUMENTS / DIVERS
A64: Désignation | B64: Montant | C64: Unité
A65: Établissement DOE | B65: 500 | C65: forfait
A66: Établissement Carnet soudures | B66: 1000 | C66: forfait
A67: Plan isométrique par SCR | B67: 800 | C67: forfait

Sheet Base FO
A1: BASE FOURNITURE — PRIX UNITAIRES ACHAT (MAQUETTE DE TEST)
A2: Mise à jour : test — V99
A4: 1. VANNES À SOUDER
A6: DN | B6: Vanne BS PI PN25 sans réducteur | C6: Vanne BS PI PN25 avec réducteur | D6: Vanne BS PR PN25 | E6: Vanne BS BW/F PN25 | F6: Vanne BS PEC PN25 | G6: Vanne BS PI PN40 sans réducteur
A7: 20 | B7: 30 | C7: 40 | D7: 50 | E7: 60 | F7: 70 | G7: 80
A8: 25 | B8: 35 | C8: 45 | D8: 55 | E8: 65 | F8: 75 | G8: 85
A9: 32 | B9: 42 | C9: 52 | D9: 62 | E9: 72 | F9: 82 | G9: 92
A10: 40 | B10: 50 | C10: 60 | D10: 70 | E10: 80 | F10: 90 | G10: 100
A11: 50 | B11: 60 | C11: 70 | D11: 80 | E11: 90 | F11: 100 | G11: 110
A12: 65 | B12: 75 | C12: 85 | D12: 95 | E12: 105 | F12: 115 | G12: 125
A13: 80 | B13: 90 | C13: 100 | D13: 110 | E13: 120 | F13: 130 | G13: 140
A14: 100 | B14: 110 | C14: 120 | D14: 130 | E14: 140 | F14: 150 | G14: 160
A15: 125 | B15: 135 | C15: 145 | D15: 155 | E15: 165 | F15: 175 | G15: 185
A16: 150 | B16: 160 | C16: 170 | D16: 180 | E16: 190 | F16: 200 | G16: 210
A17: 200 | B17: 210 | C17: 220 | D17: 230 | E17: 240 | F17: 250 | G17: 260
A18: 250 | B18: 260 | C18: 270 | D18: 280 | E18: 290 | F18: 300 | G18: 310
... A22: 500 | B22: 510 | C22: 520 | D22: 530 | E22: 540 | F22: 550 | G22: 560
A24: 2. VANNES LUG / BRIDES / BOULONS
A26: DN | B26: Vanne Lug PN16 | C26: Bride PN16 | D26: Boulons PN16 (lot) | E26: Vanne Lug PN25 | F26: Bride PN25 | G26: Boulons PN25 (lot) | H26: Vanne Lug PN40 | I26: Bride PN40 | J26: Joints + Boulons PN40 (lot) | K26: Joints (lot, déduit)
A27: 20 | B27: 120 | C27: 12 | D27: 5 | E27: 170 | F27: 14 | G27: 6 | H27: 220 | I27: 17 | J27: 8 | K27: 2
A28: 25 | B28: 125 | C28: 12.5 | D28: 5 | E28: 175 | F28: 14.5 | G28: 6 | H28: 225 | I28: 17.5 | J28: 8 | K28: 2
A29: 32 | B29: 132 | C29: 13.2 | D29: 5 | E29: 182 | F29: 15.2 | G29: 6 | H29: 232 | I29: 18.2 | J29: 8 | K29: 2
A30: 40 | B30: 140 | C30: 14 | D30: 5 | E30: 190 | F30: 16 | G30: 6 | H30: 240 | I30: 19 | J30: 8 | K30: 2
A31: 50 | B31: 150 | C31: 15 | D31: 5 | E31: 200 | F31: 17 | G31: 6 | H31: 250 | I31: 20 | J31: 8 | K31: 2
A32: 65 | B32: 165 | C32: 16.5 | D32: 5 | E32: 215 | F32: 18.5 | G32: 6 | H32: 265 | I32: 21.5 | J32: 8 | K32: 2
A33: 80 | B33: 180 | C33: 18 | D33: 5 | E33: 230 | F33: 20 | G33: 6 | H33: 280 | I33: 23 | J33: 8 | K33: 2
A34: 100 | B34: 200 | C34: 20 | D34: 5 | E34: 250 | F34: 22 | G34: 6 | H34: 300 | I34: 25 | J34: 8 | K34: 2
A35: 125 | B35: 225 | C35: 22.5 | D35: 5 | E35: 275 | F35: 24.5 | G35: 6 | H35: 325 | I35: 27.5 | J35: 8 | K35: 2
A36: 150 | B36: 250 | C36: 25 | D36: 5 | E36: 300 | F36: 27 | G36: 6 | H36: 350 | I36: 30 | J36: 8 | K36: 2
A37: 200 | B37: 300 | C37: 30 | D37: 5 | E37: 350 | F37: 32 | G37: 6 | H37: 400 | I37: 35 | J37: 8 | K37: 2
A38: 250 | B38: 350 | C38: 35 | D38: 5 | E38: 400 | F38: 37 | G38: 6 | H38: 450 | I38: 40 | J38: 8 | K38: 2
A39: 300 | B39: 400 | C39: 40 | D39: 5 | E39: 450 | F39: 42 | G39: 6 | H39: 500 | I39: 45 | J39: 8 | K39: 2
A41: 3. VANNES BS BRIDES / BOULONS
A43: DN | B43: Vanne BS Bride PN40 | C43: Bride PN40 | D43: Boulons PN40 (lot) | E43: Vanne BS Bride PN25 | F43: Bride PN25 | G43: Boulons PN25 (lot) | H43: Joints (lot, déduit)
A44: 20 | B44: 140 | C44: 17 | D44: 8 | E44: 130 | F44: 14 | G44: 6 | H44: 2
A45: 25 | B45: 145 | C45: 17.5 | D45: 8 | E45: 135 | F45: 14.5 | G45: 6 | H45: 2
A46: 32 | B46: 152 | C46: 18.2 | D46: 8 | E46: 142 | F46: 15.2 | G46: 6 | H46: 2
A47: 40 | B47: 160 | C47: 19 | D47: 8 | E47: 150 | F47: 16 | G47: 6 | H47: 2
A48: 50 | B48: 170 | C48: 20 | D48: 8 | E48: 160 | F48: 17 | G48: 6 | H48: 2
A49: 65 | B49: 185 | C49: 21.5 | D49: 8 | E49: 175 | F49: 18.5 | G49: 6 | H49: 2
A50: 80 | B50: 200 | C50: 23 | D50: 8 | E50: 190 | F50: 20 | G50: 6 | H50: 2
A51: 100 | B51: 220 | C51: 25 | D51: 8 | E51: 210 | F51: 22 | G51: 6 | H51: 2
A52: 125 | B52: 245 | C52: 27.5 | D52: 8 | E52: 235 | F52: 24.5 | G52: 6 | H52: 2
A53: 150 | B53: 270 | C53: 30 | D53: 8 | E53: 260 | F53: 27 | G53: 6 | H53: 2
A54: 200 | B54: 320 | C54: 35 | D54: 8 | E54: 310 | F54: 32 | G54: 6 | H54: 2
A55: 250 | B55: 370 | C55: 40 | D55: 8 | E55: 360 | F55: 37 | G55: 6 | H55: 2
A57: 4. ACCESSOIRES ACIER
A59: DN | B59: Bobines | C59: Coudes à visser | D59: Bouchon F | E59: Raccord sym. M | F59: Raccord sym. F | G59: Bouchons pompier | H59: Tubes acier 6ml | I59: Coudes à souder | J59: Fonds bombés | K59: Boulet mousse | L59: Renfort PEC (selle) | M59: Brides PN25
A60: 20 | B60: 4 | C60: 3 | D60: 2 | E60: 3 | F60: 3 | G60: 4 | H60: 30 | I60: 4 | J60: 7 | K60: 24 | L60: 12 | M60: 10
A61: 25 | B61: 4.5 | C61: 3.5 | D61: 2.25 | E61: 3 | F61: 3 | G61: 4 | H61: 35 | I61: 4.5 | J61: 7.5 | K61: 25 | L61: 12.5 | M61: 10.5
A62: 32 | B62: 5.2 | C62: 4.2 | D62: 2.6 | E62: 3 | F62: 3 | G62: 4 | H62: 42 | I62: 5.2 | J62: 8.2 | K62: 26.4 | L62: 13.2 | M62: 11.2
A63: 40 | B63: 6 | C63: 5 | D63: 3 | E63: 3 | F63: 3 | G63: 4 | H63: 50 | I63: 6 | J63: 9 | K63: 28 | L63: 14 | M63: 12
A64: 50 | B64: 7 | C64: 6 | D64: 3.5 | E64: 3 | F64: 3 | G64: 4 | H64: 60 | I64: 7 | J64: 10 | K64: 30 | L64: 15 | M64: 13
A65: 65 | B65: 8.5 | C65: 7.5 | D65: 4.25 | E65: 3 | F65: 3 | G65: 4 | H65: 75 | I65: 8.5 | J65: 11.5 | K65: 33 | L65: 16.5 | M65: 14.5
A66: 80 | B66: 10 | C66: 9 | D66: 5 | E66: 3 | F66: 3 | G66: 4 | H66: 90 | I66: 10 | J66: 13 | K66: 36 | L66: 18 | M66: 16
A67: 100 | B67: 12 | C67: 11 | D67: 6 | E67: 3 | F67: 3 | G67: 4 | H67: 110 | I67: 12 | J67: 15 | K67: 40 | L67: 20 | M67: 18
A68: 125 | B68: 14.5 | C68: 13.5 | D68: 7.25 | E68: 3 | F68: 3 | G68: 4 | H68: 135 | I68: 14.5 | J68: 17.5 | K68: 45 | L68: 22.5 | M68: 20.5
A69: 150 | B69: 17 | C69: 16 | D69: 8.5 | E69: 3 | F69: 3 | G69: 4 | H69: 160 | I69: 17 | J69: 20 | K69: 50 | L69: 25 | M69: 23
A70: 200 | B70: 22 | C70: 21 | D70: 11 | E70: 3 | F70: 3 | G70: 4 | H70: 210 | I70: 22 | J70: 25 | K70: 60 | L70: 30 | M70: 28
A71: 250 | B71: 27 | C71: 26 | D71: 13.5 | E71: 3 | F71: 3 | G71: 4 | H71: 260 | I71: 27 | J71: 30 | K71: 70 | L71: 35 | M71: 33
... A75: 500 | B75: 52 | C75: 51 | D75: 26 | E75: 3 | F75: 3 | G75: 4 | H75: 510 | I75: 52 | J75: 55 | K75: 120 | L75: 60 | M75: 58
A77: 5. COLLIERS CENTREURS
A79: DN Isolation | B79: Nb segments par collier | C79: Prix unitaire segment
A80: 90 | B80: 2 | C80: 12
A81: 110 | B81: 2 | C81: 12
A82: 125 | B82: 2 | C82: 12
A83: 140 | B83: 2 | C83: 12
A84: 160 | B84: 2 | C84: 12
A85: 180 | B85: 2 | C85: 12
A86: 200 | B86: 3 | C86: 12
A87: 225 | B87: 3 | C87: 12
A88: 250 | B88: 3 | C88: 12
A89: 280 | B89: 3 | C89: 12
A90: 315 | B90: 3 | C90: 12
A91: 355 | B91: 3 | C91: 12
... A98: 800 | B98: 4 | C98: 12
A100: 6. ISOLATION (diamètres extérieurs)
A102: DN Acier | B102: Ø ISO 1 | C102: Ø ISO 2 | D102: Ø ISO 3 | E102: Poids kg/ml | F102: Volume/ml Iso 1 | G102: Volume/ml Iso 2 | H102: Volume/ml Iso 3 | I102: Ø intérieur (mm) | J102: Nb coupes / jour (en 5 ml)
A103: 20 | B103: 90 | C103: 110 | D103: 125 | E103: 2 | F103: 0.00636 | G103: 0.0095 | H103: 0.01227 | I103: 20 | J103: 48
A104: 25 | B104: 90 | C104: 110 | D104: 125 | E104: 2.5 | F104: 0.00636 | G104: 0.0095 | H104: 0.01227 | I104: 25 | J104: 48
A105: 32 | B105: 110 | C105: 125 | D105: 140 | E105: 3.2 | F105: 0.0095 | G105: 0.01227 | H105: 0.01539 | I105: 32 | J105: 48
A106: 40 | B106: 110 | C106: 125 | D106: 140 | E106: 4 | F106: 0.0095 | G106: 0.01227 | H106: 0.01539 | I106: 40 | J106: 48
A107: 50 | B107: 125 | C107: 140 | D107: 160 | E107: 5 | F107: 0.01227 | G107: 0.01539 | H107: 0.02011 | I107: 50 | J107: 48
A108: 65 | B108: 140 | C108: 160 | D108: 180 | E108: 6.5 | F108: 0.01539 | G108: 0.02011 | H108: 0.02545 | I108: 65 | J108: 48
A109: 80 | B109: 160 | C109: 180 | D109: 200 | E109: 8 | F109: 0.02011 | G109: 0.02545 | H109: 0.03142 | I109: 80 | J109: 48
A110: 100 | B110: 200 | C110: 225 | D110: 250 | E110: 10 | F110: 0.03142 | G110: 0.03976 | H110: 0.04909 | I110: 100 | J110: 48
A111: 125 | B111: 225 | C111: 250 | D111: 280 | E111: 12.5 | F111: 0.03976 | G111: 0.04909 | H111: 0.06158 | I111: 125 | J111: 24
A112: 150 | B112: 250 | C112: 280 | D112: 315 | E112: 15 | F112: 0.04909 | G112: 0.06158 | H112: 0.07793 | I112: 150 | J112: 24
A113: 200 | B113: 315 | C113: 355 | D113: 400 | E113: 20 | F113: 0.07793 | G113: 0.09898 | H113: 0.12566 | I113: 200 | J113: 24
A114: 250 | B114: 400 | C114: 450 | D114: 500 | E114: 25 | F114: 0.12566 | G114: 0.15904 | H114: 0.19635 | I114: 250 | J114: 24
... A120: 600 | B120: 800 | C120: 900 | D120: 1000 | E120: 60 | F120: 0.50265 | G120: 0.63617 | H120: 0.7854 | I120: 600 | J120: 24
A122: 7b. FORFAITS PAR DISTANCE
A124: Poste | B124: 0-100 km | C124: 100-150 km | D124: 150-200 km | E124: 200-300 km | F124: 300-500 km | G124: > 500 km (€/km supp)
A125: Mob/Démob Radio | B125: 1000 | C125: 1200 | D125: 1500 | E125: 2000 | F125: 3000 | G125: 5
A126: Mob/Démob Ultrasons | B126: 800 | C126: 1000 | D126: 1200 | E126: 1600 | F126: 2400 | G126: 4
A127: Mob/Démob Ressuage | B127: 600 | C127: 800 | D127: 1000 | E127: 1300 | F127: 2000 | G127: 3
A129: 7c. PRIX PAR FILM / CONTRÔLE (par tranche DN)
A131: Tranche DN | B131: Radio | C131: Ultrasons | D131: Ressuage | E131: DN min | F131: DN max
A132: DN 15 à 65 | B132: 50 | C132: 40 | D132: 30 | E132: 15 | F132: 65
A133: DN 80 à 200 | B133: 100 | C133: 80 | D133: 60 | E133: 80 | F133: 200
...

Sheet Base Opération
A1: BASE OPÉRATION — PANIERS (MAQUETTE DE TEST)
A3: RÉFÉRENCE ÉQUIPES
A5: Code | B5: Nb pers | C5: Taux horaire
A6: S | B6: 1 | C6: 100
A7: S+T | B7: 2 | C7: 190
A8: S+T+P | B8: 3 | C8: 275
A9: M | B9: 1 | C9: 80
A10: M+M | B10: 2 | C10: 160
A11: OS | B11: 1 | C11: 100
A12: OS+OS | B12: 2 | C12: 200
A13: OS+OS+OS | B13: 3 | C13: 300
A15: PURGE
A17: DN | B17: Équipe | C17: Nb heures | D17: Taux horaire | E17: Montant MO | F17: Vanne ×2 | G17: Bobine | H17: Coude ×4 | I17: Bouchon ×2 | J17: Bande grasse | K17: Peinture | L17: Purgeur auto ×2 | M17: Tés acier | N17: Total Fourn. | O17: TOTAL
A18: 20 | B18: S+T | C18: =2*'Base MO'!$G$5/VLOOKUP(A18,'Base MO'!$A$24:$F$41,3,FALSE) | D18: 190 | F18: =2*VLOOKUP(A18,FO_Vannes_Souder[],4,FALSE) | G18: =VLOOKUP(A18,FO_Accessoires_Acier[],2,FALSE) | H18: =4*VLOOKUP(A18,FO_Accessoires_Acier[],3,FALSE) | I18: =2*VLOOKUP(A18,FO_Accessoires_Acier[],4,FALSE) | J18: 50 | K18: 25 | L18: =2*FO_Purgeur_Auto | M18: =FO_Te_Acier
A19: 25 | B19: S+T | C19: =2*'Base MO'!$G$5/VLOOKUP(A19,'Base MO'!$A$24:$F$41,3,FALSE) | D19: 190 | F19: =2*VLOOKUP(A19,FO_Vannes_Souder[],4,FALSE) | G19: =VLOOKUP(A19,FO_Accessoires_Acier[],2,FALSE) | H19: =4*VLOOKUP(A19,FO_Accessoires_Acier[],3,FALSE) | I19: =2*VLOOKUP(A19,FO_Accessoires_Acier[],4,FALSE) | J19: 50 | K19: 25 | L19: =2*FO_Purgeur_Auto | M19: =FO_Te_Acier
A20: 32 | B20: S+T | C20: =2*'Base MO'!$G$5/VLOOKUP(A20,'Base MO'!$A$24:$F$41,3,FALSE) | D20: 190 | F20: =2*VLOOKUP(A20,FO_Vannes_Souder[],4,FALSE) | G20: =VLOOKUP(A20,FO_Accessoires_Acier[],2,FALSE) | H20: =4*VLOOKUP(A20,FO_Accessoires_Acier[],3,FALSE) | I20: =2*VLOOKUP(A20,FO_Accessoires_Acier[],4,FALSE) | J20: 50 | K20: 25 | L20: =2*FO_Purgeur_Auto | M20: =FO_Te_Acier
A21: 40 | B21: S+T | C21: =2*'Base MO'!$G$5/VLOOKUP(A21,'Base MO'!$A$24:$F$41,3,FALSE) | D21: 190 | F21: =2*VLOOKUP(A21,FO_Vannes_Souder[],4,FALSE) | G21: =VLOOKUP(A21,FO_Accessoires_Acier[],2,FALSE) | H21: =4*VLOOKUP(A21,FO_Accessoires_Acier[],3,FALSE) | I21: =2*VLOOKUP(A21,FO_Accessoires_Acier[],4,FALSE) | J21: 50 | K21: 25 | L21: =2*FO_Purgeur_Auto | M21: =FO_Te_Acier
A22: 50 | B22: S+T | C22: =2*'Base MO'!$G$5/VLOOKUP(A22,'Base MO'!$A$24:$F$41,3,FALSE) | D22: 190 | F22: =2*VLOOKUP(A22,FO_Vannes_Souder[],4,FALSE) | G22: =VLOOKUP(A22,FO_Accessoires_Acier[],2,FALSE) | H22: =4*VLOOKUP(A22,FO_Accessoires_Acier[],3,FALSE) | I22: =2*VLOOKUP(A22,FO_Accessoires_Acier[],4,FALSE) | J22: 50 | K22: 25 | L22: =2*FO_Purgeur_Auto | M22: =FO_Te_Acier
A23: 65 | B23: S+T | C23: =2*'Base MO'!$G$5/VLOOKUP(A23,'Base MO'!$A$24:$F$41,3,FALSE) | D23: 190 | F23: =2*VLOOKUP(A23,FO_Vannes_Souder[],4,FALSE) | G23: =VLOOKUP(A23,FO_Accessoires_Acier[],2,FALSE) | H23: =4*VLOOKUP(A23,FO_Accessoires_Acier[],3,FALSE) | I23: =2*VLOOKUP(A23,FO_Accessoires_Acier[],4,FALSE) | J23: 50 | K23: 25 | L23: =2*FO_Purgeur_Auto | M23: =FO_Te_Acier
A24: 80 | B24: S+T | C24: =2*'Base MO'!$G$5/VLOOKUP(A24,'Base MO'!$A$24:$F$41,3,FALSE) | D24: 190 | F24: =2*VLOOKUP(A24,FO_Vannes_Souder[],4,FALSE) | G24: =VLOOKUP(A24,FO_Accessoires_Acier[],2,FALSE) | H24: =4*VLOOKUP(A24,FO_Accessoires_Acier[],3,FALSE) | I24: =2*VLOOKUP(A24,FO_Accessoires_Acier[],4,FALSE) | J24: 50 | K24: 25 | L24: =2*FO_Purgeur_Auto | M24: =FO_Te_Acier
A25: 100 | B25: S+T | C25: =2*'Base MO'!$G$5/VLOOKUP(A25,'Base MO'!$A$24:$F$41,3,FALSE) | D25: 190 | F25: =2*VLOOKUP(A25,FO_Vannes_Souder[],4,FALSE) | G25: =VLOOKUP(A25,FO_Accessoires_Acier[],2,FALSE) | H25: =4*VLOOKUP(A25,FO_Accessoires_Acier[],3,FALSE) | I25: =2*VLOOKUP(A25,FO_Accessoires_Acier[],4,FALSE) | J25: 50 | K25: 25 | L25: =2*FO_Purgeur_Auto | M25: =FO_Te_Acier
A27: VIDANGE ASPIRATION
A29: DN | B29: Équipe | C29: Nb heures | D29: Taux horaire | E29: Montant MO | F29: Vanne ×2 | G29: Bobine | H29: Racc. pomp. F ×2 | I29: Bouch. pomp. ×2 | J29: Bande grasse | K29: Peinture | L29: Total Fourn. | M29: TOTAL
A30: 20 | B30: S+T | C30: =2*'Base MO'!$G$5/VLOOKUP(A30,'Base MO'!$A$24:$F$41,3,FALSE) | D30: 190 | F30: =2*VLOOKUP(A30,FO_Vannes_Souder[],4,FALSE) | G30: =VLOOKUP(A30,FO_Accessoires_Acier[],2,FALSE) | H30: =2*VLOOKUP(A30,FO_Accessoires_Acier[],6,FALSE) | I30: =2*VLOOKUP(A30,FO_Accessoires_Acier[],7,FALSE) | J30: 50 | K30: 25
A31: 25 | B31: S+T | C31: =2*'Base MO'!$G$5/VLOOKUP(A31,'Base MO'!$A$24:$F$41,3,FALSE) | D31: 190 | F31: =2*VLOOKUP(A31,FO_Vannes_Souder[],4,FALSE) | G31: =VLOOKUP(A31,FO_Accessoires_Acier[],2,FALSE) | H31: =2*VLOOKUP(A31,FO_Accessoires_Acier[],6,FALSE) | I31: =2*VLOOKUP(A31,FO_Accessoires_Acier[],7,FALSE) | J31: 50 | K31: 25
A32: 32 | B32: S+T | C32: =2*'Base MO'!$G$5/VLOOKUP(A32,'Base MO'!$A$24:$F$41,3,FALSE) | D32: 190 | F32: =2*VLOOKUP(A32,FO_Vannes_Souder[],4,FALSE) | G32: =VLOOKUP(A32,FO_Accessoires_Acier[],2,FALSE) | H32: =2*VLOOKUP(A32,FO_Accessoires_Acier[],6,FALSE) | I32: =2*VLOOKUP(A32,FO_Accessoires_Acier[],7,FALSE) | J32: 50 | K32: 25
A33: 40 | B33: S+T | C33: =2*'Base MO'!$G$5/VLOOKUP(A33,'Base MO'!$A$24:$F$41,3,FALSE) | D33: 190 | F33: =2*VLOOKUP(A33,FO_Vannes_Souder[],4,FALSE) | G33: =VLOOKUP(A33,FO_Accessoires_Acier[],2,FALSE) | H33: =2*VLOOKUP(A33,FO_Accessoires_Acier[],6,FALSE) | I33: =2*VLOOKUP(A33,FO_Accessoires_Acier[],7,FALSE) | J33: 50 | K33: 25
A34: 50 | B34: S+T | C34: =2*'Base MO'!$G$5/VLOOKUP(A34,'Base MO'!$A$24:$F$41,3,FALSE) | D34: 190 | F34: =2*VLOOKUP(A34,FO_Vannes_Souder[],4,FALSE) | G34: =VLOOKUP(A34,FO_Accessoires_Acier[],2,FALSE) | H34: =2*VLOOKUP(A34,FO_Accessoires_Acier[],6,FALSE) | I34: =2*VLOOKUP(A34,FO_Accessoires_Acier[],7,FALSE) | J34: 50 | K34: 25
A35: 65 | B35: S+T | C35: =2*'Base MO'!$G$5/VLOOKUP(A35,'Base MO'!$A$24:$F$41,3,FALSE) | D35: 190 | F35: =2*VLOOKUP(A35,FO_Vannes_Souder[],4,FALSE) | G35: =VLOOKUP(A35,FO_Accessoires_Acier[],2,FALSE) | H35: =2*VLOOKUP(A35,FO_Accessoires_Acier[],6,FALSE) | I35: =2*VLOOKUP(A35,FO_Accessoires_Acier[],7,FALSE) | J35: 50 | K35: 25
A36: 80 | B36: S+T | C36: =2*'Base MO'!$G$5/VLOOKUP(A36,'Base MO'!$A$24:$F$41,3,FALSE) | D36: 190 | F36: =2*VLOOKUP(A36,FO_Vannes_Souder[],4,FALSE) | G36: =VLOOKUP(A36,FO_Accessoires_Acier[],2,FALSE) | H36: =2*VLOOKUP(A36,FO_Accessoires_Acier[],6,FALSE) | I36: =2*VLOOKUP(A36,FO_Accessoires_Acier[],7,FALSE) | J36: 50 | K36: 25
A37: 100 | B37: S+T | C37: =2*'Base MO'!$G$5/VLOOKUP(A37,'Base MO'!$A$24:$F$41,3,FALSE) | D37: 190 | F37: =2*VLOOKUP(A37,FO_Vannes_Souder[],4,FALSE) | G37: =VLOOKUP(A37,FO_Accessoires_Acier[],2,FALSE) | H37: =2*VLOOKUP(A37,FO_Accessoires_Acier[],6,FALSE) | I37: =2*VLOOKUP(A37,FO_Accessoires_Acier[],7,FALSE) | J37: 50 | K37: 25
A39: VIDANGE GRAVITÉ
A41: DN | B41: Équipe | C41: Nb heures | D41: Taux horaire | E41: Montant MO | F41: Coude souder ×2 | G41: Bande grasse | H41: Peinture | I41: Rallonge | J41: Total Fourn. | K41: TOTAL | L41: Vanne ×2
A42: 20 | B42: S+T | C42: =2*'Base MO'!$G$5/VLOOKUP(A42,'Base MO'!$A$24:$F$41,3,FALSE) | D42: 190 | F42: =2*VLOOKUP(A42,FO_Accessoires_Acier[],9,FALSE) | G42: 50 | H42: 25 | I42: =FO_Rallonge_Vanne_Preisolee | L42: =2*VLOOKUP(A42,FO_Vannes_Souder[],4,FALSE)
A43: 25 | B43: S+T | C43: =2*'Base MO'!$G$5/VLOOKUP(A43,'Base MO'!$A$24:$F$41,3,FALSE) | D43: 190 | F43: =2*VLOOKUP(A43,FO_Accessoires_Acier[],9,FALSE) | G43: 50 | H43: 25 | I43: =FO_Rallonge_Vanne_Preisolee | L43: =2*VLOOKUP(A43,FO_Vannes_Souder[],4,FALSE)
A44: 32 | B44: S+T | C44: =2*'Base MO'!$G$5/VLOOKUP(A44,'Base MO'!$A$24:$F$41,3,FALSE) | D44: 190 | F44: =2*VLOOKUP(A44,FO_Accessoires_Acier[],9,FALSE) | G44: 50 | H44: 25 | I44: =FO_Rallonge_Vanne_Preisolee | L44: =2*VLOOKUP(A44,FO_Vannes_Souder[],4,FALSE)
A45: 40 | B45: S+T | C45: =2*'Base MO'!$G$5/VLOOKUP(A45,'Base MO'!$A$24:$F$41,3,FALSE) | D45: 190 | F45: =2*VLOOKUP(A45,FO_Accessoires_Acier[],9,FALSE) | G45: 50 | H45: 25 | I45: =FO_Rallonge_Vanne_Preisolee | L45: =2*VLOOKUP(A45,FO_Vannes_Souder[],4,FALSE)
A46: 50 | B46: S+T | C46: =2*'Base MO'!$G$5/VLOOKUP(A46,'Base MO'!$A$24:$F$41,3,FALSE) | D46: 190 | F46: =2*VLOOKUP(A46,FO_Accessoires_Acier[],9,FALSE) | G46: 50 | H46: 25 | I46: =FO_Rallonge_Vanne_Preisolee | L46: =2*VLOOKUP(A46,FO_Vannes_Souder[],4,FALSE)
A47: 65 | B47: S+T | C47: =2*'Base MO'!$G$5/VLOOKUP(A47,'Base MO'!$A$24:$F$41,3,FALSE) | D47: 190 | F47: =2*VLOOKUP(A47,FO_Accessoires_Acier[],9,FALSE) | G47: 50 | H47: 25 | I47: =FO_Rallonge_Vanne_Preisolee | L47: =2*VLOOKUP(A47,FO_Vannes_Souder[],4,FALSE)
A48: 80 | B48: S+T | C48: =2*'Base MO'!$G$5/VLOOKUP(A48,'Base MO'!$A$24:$F$41,3,FALSE) | D48: 190 | F48: =2*VLOOKUP(A48,FO_Accessoires_Acier[],9,FALSE) | G48: 50 | H48: 25 | I48: =FO_Rallonge_Vanne_Preisolee | L48: =2*VLOOKUP(A48,FO_Vannes_Souder[],4,FALSE)
A49: 100 | B49: S+T | C49: =2*'Base MO'!$G$5/VLOOKUP(A49,'Base MO'!$A$24:$F$41,3,FALSE) | D49: 190 | F49: =2*VLOOKUP(A49,FO_Accessoires_Acier[],9,FALSE) | G49: 50 | H49: 25 | I49: =FO_Rallonge_Vanne_Preisolee | L49: =2*VLOOKUP(A49,FO_Vannes_Souder[],4,FALSE)
A51: BY-PASS - FONDS BOMBÉS
C53: Heures | F53: MO | H53: Fournitures | L53: Total fourn. | N53: TOTAL
A54: DN | B54: Équipe | C54: BY-PASS | D54: FONDS BOMBÉS | E54: Taux horaire | F54: BY-PASS | G54: FONDS BOMBÉS | H54: Coude ×2 | I54: Vanne DN20 ×1 | J54: Fonds bomb. ×2 | K54: Peinture | L54: BY-PASS | M54: FONDS BOMBÉS | N54: BY-PASS | O54: FONDS BOMBÉS
A55: 20 | B55: S+T | C55: 4 | D55: 2 | E55: 190 | F55: 760 | G55: 380 | H55: 10 | I55: 30 | J55: 20 | K55: 20 | L55: 60 | M55: 70 | N55: 820 | O55: 450
A56: 25 | B56: S+T | C56: 4 | D56: 2 | E56: 190 | F56: 760 | G56: 380 | H56: 10 | I56: 30 | J56: 20 | K56: 20 | L56: 60 | M56: 70 | N56: 820 | O56: 450
A57: 32 | B57: S+T | C57: 4 | D57: 2 | E57: 190 | F57: 760 | G57: 380 | H57: 10 | I57: 30 | J57: 20 | K57: 20 | L57: 60 | M57: 70 | N57: 820 | O57: 450
A58: 40 | B58: S+T | C58: 4 | D58: 2 | E58: 190 | F58: 760 | G58: 380 | H58: 10 | I58: 30 | J58: 20 | K58: 20 | L58: 60 | M58: 70 | N58: 820 | O58: 450
A59: 50 | B59: S+T | C59: 4 | D59: 2 | E59: 190 | F59: 760 | G59: 380 | H59: 10 | I59: 30 | J59: 20 | K59: 20 | L59: 60 | M59: 70 | N59: 820 | O59: 450
A60: 65 | B60: S+T | C60: 4 | D60: 2 | E60: 190 | F60: 760 | G60: 380 | H60: 10 | I60: 30 | J60: 20 | K60: 20 | L60: 60 | M60: 70 | N60: 820 | O60: 450
A61: 80 | B61: S+T | C61: 4 | D61: 2 | E61: 190 | F61: 760 | G61: 380 | H61: 10 | I61: 30 | J61: 20 | K61: 20 | L61: 60 | M61: 70 | N61: 820 | O61: 450
A62: 100 | B62: S+T | C62: 4 | D62: 2 | E62: 190 | F62: 760 | G62: 380 | H62: 10 | I62: 30 | J62: 20 | K62: 20 | L62: 60 | M62: 70 | N62: 820 | O62: 450
A64: Boîtiers Plexo + pose (ajouté à chaque vanne SST) | B64: 60
A66: SST — VANNES BS PN25
A68: DN | B68: Équipe | C68: Nb heures | D68: Taux horaire | E68: Montant MO | F68: Vanne BS ×2 | G68: Peinture | H68: Total Fourn. | I68: TOTAL
A69: 20 | B69: S+T | C69: =2*'Base MO'!$G$5/VLOOKUP(A69,'Base MO'!$A$24:$F$41,3,FALSE) | D69: 190 | F69: =2*VLOOKUP(A69,FO_Vannes_Souder[],2,FALSE) | G69: =IF($A69>=FO_Peinture_SST_Seuil_DN,FO_Peinture_SST_Gros_DN,FO_Peinture_SST_Petit_DN)
A70: 25 | B70: S+T | C70: =2*'Base MO'!$G$5/VLOOKUP(A70,'Base MO'!$A$24:$F$41,3,FALSE) | D70: 190 | F70: =2*VLOOKUP(A70,FO_Vannes_Souder[],2,FALSE) | G70: =IF($A70>=FO_Peinture_SST_Seuil_DN,FO_Peinture_SST_Gros_DN,FO_Peinture_SST_Petit_DN)
A71: 32 | B71: S+T | C71: =2*'Base MO'!$G$5/VLOOKUP(A71,'Base MO'!$A$24:$F$41,3,FALSE) | D71: 190 | F71: =2*VLOOKUP(A71,FO_Vannes_Souder[],2,FALSE) | G71: =IF($A71>=FO_Peinture_SST_Seuil_DN,FO_Peinture_SST_Gros_DN,FO_Peinture_SST_Petit_DN)
A72: 40 | B72: S+T | C72: =2*'Base MO'!$G$5/VLOOKUP(A72,'Base MO'!$A$24:$F$41,3,FALSE) | D72: 190 | F72: =2*VLOOKUP(A72,FO_Vannes_Souder[],2,FALSE) | G72: =IF($A72>=FO_Peinture_SST_Seuil_DN,FO_Peinture_SST_Gros_DN,FO_Peinture_SST_Petit_DN)
A73: 50 | B73: S+T | C73: =2*'Base MO'!$G$5/VLOOKUP(A73,'Base MO'!$A$24:$F$41,3,FALSE) | D73: 190 | F73: =2*VLOOKUP(A73,FO_Vannes_Souder[],2,FALSE) | G73: =IF($A73>=FO_Peinture_SST_Seuil_DN,FO_Peinture_SST_Gros_DN,FO_Peinture_SST_Petit_DN)
A74: 65 | B74: S+T | C74: =2*'Base MO'!$G$5/VLOOKUP(A74,'Base MO'!$A$24:$F$41,3,FALSE) | D74: 190 | F74: =2*VLOOKUP(A74,FO_Vannes_Souder[],2,FALSE) | G74: =IF($A74>=FO_Peinture_SST_Seuil_DN,FO_Peinture_SST_Gros_DN,FO_Peinture_SST_Petit_DN)
A75: 80 | B75: S+T | C75: =2*'Base MO'!$G$5/VLOOKUP(A75,'Base MO'!$A$24:$F$41,3,FALSE) | D75: 190 | F75: =2*VLOOKUP(A75,FO_Vannes_Souder[],2,FALSE) | G75: =IF($A75>=FO_Peinture_SST_Seuil_DN,FO_Peinture_SST_Gros_DN,FO_Peinture_SST_Petit_DN)
A76: 100 | B76: S+T | C76: =2*'Base MO'!$G$5/VLOOKUP(A76,'Base MO'!$A$24:$F$41,3,FALSE) | D76: 190 | F76: =2*VLOOKUP(A76,FO_Vannes_Souder[],2,FALSE) | G76: =IF($A76>=FO_Peinture_SST_Seuil_DN,FO_Peinture_SST_Gros_DN,FO_Peinture_SST_Petit_DN)
A78: SST — VANNES BS PN40
A80: DN | B80: Équipe | C80: Nb heures | D80: Taux horaire | E80: Montant MO | F80: Vanne BS ×2 | G80: Peinture | H80: Total Fourn. | I80: TOTAL
A81: 20 | B81: S+T | C81: =2*'Base MO'!$G$5/VLOOKUP(A81,'Base MO'!$A$24:$F$41,3,FALSE) | D81: 190 | F81: =2*VLOOKUP(A81,FO_Vannes_Souder[],7,FALSE) | G81: =IF($A81>=FO_Peinture_SST_Seuil_DN,FO_Peinture_SST_Gros_DN,FO_Peinture_SST_Petit_DN)
A82: 25 | B82: S+T | C82: =2*'Base MO'!$G$5/VLOOKUP(A82,'Base MO'!$A$24:$F$41,3,FALSE) | D82: 190 | F82: =2*VLOOKUP(A82,FO_Vannes_Souder[],7,FALSE) | G82: =IF($A82>=FO_Peinture_SST_Seuil_DN,FO_Peinture_SST_Gros_DN,FO_Peinture_SST_Petit_DN)
A83: 32 | B83: S+T | C83: =2*'Base MO'!$G$5/VLOOKUP(A83,'Base MO'!$A$24:$F$41,3,FALSE) | D83: 190 | F83: =2*VLOOKUP(A83,FO_Vannes_Souder[],7,FALSE) | G83: =IF($A83>=FO_Peinture_SST_Seuil_DN,FO_Peinture_SST_Gros_DN,FO_Peinture_SST_Petit_DN)
A84: 40 | B84: S+T | C84: =2*'Base MO'!$G$5/VLOOKUP(A84,'Base MO'!$A$24:$F$41,3,FALSE) | D84: 190 | F84: =2*VLOOKUP(A84,FO_Vannes_Souder[],7,FALSE) | G84: =IF($A84>=FO_Peinture_SST_Seuil_DN,FO_Peinture_SST_Gros_DN,FO_Peinture_SST_Petit_DN)
A85: 50 | B85: S+T | C85: =2*'Base MO'!$G$5/VLOOKUP(A85,'Base MO'!$A$24:$F$41,3,FALSE) | D85: 190 | F85: =2*VLOOKUP(A85,FO_Vannes_Souder[],7,FALSE) | G85: =IF($A85>=FO_Peinture_SST_Seuil_DN,FO_Peinture_SST_Gros_DN,FO_Peinture_SST_Petit_DN)
A86: 65 | B86: S+T | C86: =2*'Base MO'!$G$5/VLOOKUP(A86,'Base MO'!$A$24:$F$41,3,FALSE) | D86: 190 | F86: =2*VLOOKUP(A86,FO_Vannes_Souder[],7,FALSE) | G86: =IF($A86>=FO_Peinture_SST_Seuil_DN,FO_Peinture_SST_Gros_DN,FO_Peinture_SST_Petit_DN)
A87: 80 | B87: S+T | C87: =2*'Base MO'!$G$5/VLOOKUP(A87,'Base MO'!$A$24:$F$41,3,FALSE) | D87: 190 | F87: =2*VLOOKUP(A87,FO_Vannes_Souder[],7,FALSE) | G87: =IF($A87>=FO_Peinture_SST_Seuil_DN,FO_Peinture_SST_Gros_DN,FO_Peinture_SST_Petit_DN)
A88: 100 | B88: S+T | C88: =2*'Base MO'!$G$5/VLOOKUP(A88,'Base MO'!$A$24:$F$41,3,FALSE) | D88: 190 | F88: =2*VLOOKUP(A88,FO_Vannes_Souder[],7,FALSE) | G88: =IF($A88>=FO_Peinture_SST_Seuil_DN,FO_Peinture_SST_Gros_DN,FO_Peinture_SST_Petit_DN)
A90: SST — VANNES PAP PN25
A92: DN | B92: Équipe | C92: Nb heures | D92: Taux horaire | E92: Montant MO | F92: Brides ×4 | G92: Vanne lug ×2 | H92: Boulonnerie + joints | I92: Peinture | J92: Total Fourn. | K92: TOTAL
A93: 20 | B93: S+T | C93: =3*'Base MO'!$G$5/VLOOKUP(A93,'Base MO'!$A$24:$F$41,3,FALSE) | D93: 190 | F93: =4*VLOOKUP(A93,FO_Vannes_Brides_PN16_PN25_PN40[],6,FALSE) | G93: =2*VLOOKUP(A93,FO_Vannes_Brides_PN16_PN25_PN40[],5,FALSE) | H93: =VLOOKUP(A93,FO_Vannes_Brides_PN16_PN25_PN40[],7,FALSE)+VLOOKUP(A93,FO_Vannes_Brides_PN16_PN25_PN40[],11,FALSE) | I93: =IF($A93>=FO_Peinture_SST_Seuil_DN,FO_Peinture_SST_Gros_DN,FO_Peinture_SST_Petit_DN)
A94: 25 | B94: S+T | C94: =3*'Base MO'!$G$5/VLOOKUP(A94,'Base MO'!$A$24:$F$41,3,FALSE) | D94: 190 | F94: =4*VLOOKUP(A94,FO_Vannes_Brides_PN16_PN25_PN40[],6,FALSE) | G94: =2*VLOOKUP(A94,FO_Vannes_Brides_PN16_PN25_PN40[],5,FALSE) | H94: =VLOOKUP(A94,FO_Vannes_Brides_PN16_PN25_PN40[],7,FALSE)+VLOOKUP(A94,FO_Vannes_Brides_PN16_PN25_PN40[],11,FALSE) | I94: =IF($A94>=FO_Peinture_SST_Seuil_DN,FO_Peinture_SST_Gros_DN,FO_Peinture_SST_Petit_DN)
A95: 32 | B95: S+T | C95: =3*'Base MO'!$G$5/VLOOKUP(A95,'Base MO'!$A$24:$F$41,3,FALSE) | D95: 190 | F95: =4*VLOOKUP(A95,FO_Vannes_Brides_PN16_PN25_PN40[],6,FALSE) | G95: =2*VLOOKUP(A95,FO_Vannes_Brides_PN16_PN25_PN40[],5,FALSE) | H95: =VLOOKUP(A95,FO_Vannes_Brides_PN16_PN25_PN40[],7,FALSE)+VLOOKUP(A95,FO_Vannes_Brides_PN16_PN25_PN40[],11,FALSE) | I95: =IF($A95>=FO_Peinture_SST_Seuil_DN,FO_Peinture_SST_Gros_DN,FO_Peinture_SST_Petit_DN)
A96: 40 | B96: S+T | C96: =3*'Base MO'!$G$5/VLOOKUP(A96,'Base MO'!$A$24:$F$41,3,FALSE) | D96: 190 | F96: =4*VLOOKUP(A96,FO_Vannes_Brides_PN16_PN25_PN40[],6,FALSE) | G96: =2*VLOOKUP(A96,FO_Vannes_Brides_PN16_PN25_PN40[],5,FALSE) | H96: =VLOOKUP(A96,FO_Vannes_Brides_PN16_PN25_PN40[],7,FALSE)+VLOOKUP(A96,FO_Vannes_Brides_PN16_PN25_PN40[],11,FALSE) | I96: =IF($A96>=FO_Peinture_SST_Seuil_DN,FO_Peinture_SST_Gros_DN,FO_Peinture_SST_Petit_DN)
A97: 50 | B97: S+T | C97: =3*'Base MO'!$G$5/VLOOKUP(A97,'Base MO'!$A$24:$F$41,3,FALSE) | D97: 190 | F97: =4*VLOOKUP(A97,FO_Vannes_Brides_PN16_PN25_PN40[],6,FALSE) | G97: =2*VLOOKUP(A97,FO_Vannes_Brides_PN16_PN25_PN40[],5,FALSE) | H97: =VLOOKUP(A97,FO_Vannes_Brides_PN16_PN25_PN40[],7,FALSE)+VLOOKUP(A97,FO_Vannes_Brides_PN16_PN25_PN40[],11,FALSE) | I97: =IF($A97>=FO_Peinture_SST_Seuil_DN,FO_Peinture_SST_Gros_DN,FO_Peinture_SST_Petit_DN)
A98: 65 | B98: S+T | C98: =3*'Base MO'!$G$5/VLOOKUP(A98,'Base MO'!$A$24:$F$41,3,FALSE) | D98: 190 | F98: =4*VLOOKUP(A98,FO_Vannes_Brides_PN16_PN25_PN40[],6,FALSE) | G98: =2*VLOOKUP(A98,FO_Vannes_Brides_PN16_PN25_PN40[],5,FALSE) | H98: =VLOOKUP(A98,FO_Vannes_Brides_PN16_PN25_PN40[],7,FALSE)+VLOOKUP(A98,FO_Vannes_Brides_PN16_PN25_PN40[],11,FALSE) | I98: =IF($A98>=FO_Peinture_SST_Seuil_DN,FO_Peinture_SST_Gros_DN,FO_Peinture_SST_Petit_DN)
A99: 80 | B99: S+T | C99: =3*'Base MO'!$G$5/VLOOKUP(A99,'Base MO'!$A$24:$F$41,3,FALSE) | D99: 190 | F99: =4*VLOOKUP(A99,FO_Vannes_Brides_PN16_PN25_PN40[],6,FALSE) | G99: =2*VLOOKUP(A99,FO_Vannes_Brides_PN16_PN25_PN40[],5,FALSE) | H99: =VLOOKUP(A99,FO_Vannes_Brides_PN16_PN25_PN40[],7,FALSE)+VLOOKUP(A99,FO_Vannes_Brides_PN16_PN25_PN40[],11,FALSE) | I99: =IF($A99>=FO_Peinture_SST_Seuil_DN,FO_Peinture_SST_Gros_DN,FO_Peinture_SST_Petit_DN)
A100: 100 | B100: S+T | C100: =3*'Base MO'!$G$5/VLOOKUP(A100,'Base MO'!$A$24:$F$41,3,FALSE) | D100: 190 | F100: =4*VLOOKUP(A100,FO_Vannes_Brides_PN16_PN25_PN40[],6,FALSE) | G100: =2*VLOOKUP(A100,FO_Vannes_Brides_PN16_PN25_PN40[],5,FALSE) | H100: =VLOOKUP(A100,FO_Vannes_Brides_PN16_PN25_PN40[],7,FALSE)+VLOOKUP(A100,FO_Vannes_Brides_PN16_PN25_PN40[],11,FALSE) | I100: =IF($A100>=FO_Peinture_SST_Seuil_DN,FO_Peinture_SST_Gros_DN,FO_Peinture_SST_Petit_DN)
A102: SST — VANNES BS BRIDES PN25
A104: DN | B104: Équipe | C104: Nb heures | D104: Taux horaire | E104: Montant MO | F104: Brides ×4 | G104: Vanne lug ×2 | H104: Boulonnerie + joints | I104: Peinture | J104: Total Fourn. | K104: TOTAL
A105: 20 | B105: S+T | C105: =3*'Base MO'!$G$5/VLOOKUP(A105,'Base MO'!$A$24:$F$41,3,FALSE) | D105: 190 | F105: =4*VLOOKUP(A105,FO_Vannes_BS_Brides[],6,FALSE) | G105: =2*VLOOKUP(A105,FO_Vannes_BS_Brides[],5,FALSE) | H105: =VLOOKUP(A105,FO_Vannes_BS_Brides[],7,FALSE)+VLOOKUP(A105,FO_Vannes_BS_Brides[],8,FALSE) | I105: =IF($A105>=FO_Peinture_SST_Seuil_DN,FO_Peinture_SST_Gros_DN,FO_Peinture_SST_Petit_DN)
A106: 25 | B106: S+T | C106: =3*'Base MO'!$G$5/VLOOKUP(A106,'Base MO'!$A$24:$F$41,3,FALSE) | D106: 190 | F106: =4*VLOOKUP(A106,FO_Vannes_BS_Brides[],6,FALSE) | G106: =2*VLOOKUP(A106,FO_Vannes_BS_Brides[],5,FALSE) | H106: =VLOOKUP(A106,FO_Vannes_BS_Brides[],7,FALSE)+VLOOKUP(A106,FO_Vannes_BS_Brides[],8,FALSE) | I106: =IF($A106>=FO_Peinture_SST_Seuil_DN,FO_Peinture_SST_Gros_DN,FO_Peinture_SST_Petit_DN)
A107: 32 | B107: S+T | C107: =3*'Base MO'!$G$5/VLOOKUP(A107,'Base MO'!$A$24:$F$41,3,FALSE) | D107: 190 | F107: =4*VLOOKUP(A107,FO_Vannes_BS_Brides[],6,FALSE) | G107: =2*VLOOKUP(A107,FO_Vannes_BS_Brides[],5,FALSE) | H107: =VLOOKUP(A107,FO_Vannes_BS_Brides[],7,FALSE)+VLOOKUP(A107,FO_Vannes_BS_Brides[],8,FALSE) | I107: =IF($A107>=FO_Peinture_SST_Seuil_DN,FO_Peinture_SST_Gros_DN,FO_Peinture_SST_Petit_DN)
A108: 40 | B108: S+T | C108: =3*'Base MO'!$G$5/VLOOKUP(A108,'Base MO'!$A$24:$F$41,3,FALSE) | D108: 190 | F108: =4*VLOOKUP(A108,FO_Vannes_BS_Brides[],6,FALSE) | G108: =2*VLOOKUP(A108,FO_Vannes_BS_Brides[],5,FALSE) | H108: =VLOOKUP(A108,FO_Vannes_BS_Brides[],7,FALSE)+VLOOKUP(A108,FO_Vannes_BS_Brides[],8,FALSE) | I108: =IF($A108>=FO_Peinture_SST_Seuil_DN,FO_Peinture_SST_Gros_DN,FO_Peinture_SST_Petit_DN)
A109: 50 | B109: S+T | C109: =3*'Base MO'!$G$5/VLOOKUP(A109,'Base MO'!$A$24:$F$41,3,FALSE) | D109: 190 | F109: =4*VLOOKUP(A109,FO_Vannes_BS_Brides[],6,FALSE) | G109: =2*VLOOKUP(A109,FO_Vannes_BS_Brides[],5,FALSE) | H109: =VLOOKUP(A109,FO_Vannes_BS_Brides[],7,FALSE)+VLOOKUP(A109,FO_Vannes_BS_Brides[],8,FALSE) | I109: =IF($A109>=FO_Peinture_SST_Seuil_DN,FO_Peinture_SST_Gros_DN,FO_Peinture_SST_Petit_DN)
A110: 65 | B110: S+T | C110: =3*'Base MO'!$G$5/VLOOKUP(A110,'Base MO'!$A$24:$F$41,3,FALSE) | D110: 190 | F110: =4*VLOOKUP(A110,FO_Vannes_BS_Brides[],6,FALSE) | G110: =2*VLOOKUP(A110,FO_Vannes_BS_Brides[],5,FALSE) | H110: =VLOOKUP(A110,FO_Vannes_BS_Brides[],7,FALSE)+VLOOKUP(A110,FO_Vannes_BS_Brides[],8,FALSE) | I110: =IF($A110>=FO_Peinture_SST_Seuil_DN,FO_Peinture_SST_Gros_DN,FO_Peinture_SST_Petit_DN)
A111: 80 | B111: S+T | C111: =3*'Base MO'!$G$5/VLOOKUP(A111,'Base MO'!$A$24:$F$41,3,FALSE) | D111: 190 | F111: =4*VLOOKUP(A111,FO_Vannes_BS_Brides[],6,FALSE) | G111: =2*VLOOKUP(A111,FO_Vannes_BS_Brides[],5,FALSE) | H111: =VLOOKUP(A111,FO_Vannes_BS_Brides[],7,FALSE)+VLOOKUP(A111,FO_Vannes_BS_Brides[],8,FALSE) | I111: =IF($A111>=FO_Peinture_SST_Seuil_DN,FO_Peinture_SST_Gros_DN,FO_Peinture_SST_Petit_DN)
A112: 100 | B112: S+T | C112: =3*'Base MO'!$G$5/VLOOKUP(A112,'Base MO'!$A$24:$F$41,3,FALSE) | D112: 190 | F112: =4*VLOOKUP(A112,FO_Vannes_BS_Brides[],6,FALSE) | G112: =2*VLOOKUP(A112,FO_Vannes_BS_Brides[],5,FALSE) | H112: =VLOOKUP(A112,FO_Vannes_BS_Brides[],7,FALSE)+VLOOKUP(A112,FO_Vannes_BS_Brides[],8,FALSE) | I112: =IF($A112>=FO_Peinture_SST_Seuil_DN,FO_Peinture_SST_Gros_DN,FO_Peinture_SST_Petit_DN)
A114: RACCORDEMENT — INSERTION DE TÉS
A116: DN | B116: Équipe 1 | C116: Nb heures 1 | D116: Équipe 2 | E116: Nb heures 2 | F116: Montant MO | G116: Total Fourn. | H116: TOTAL
A117: 20 | B117: S+T+P | C117: 8 | D117: M | E117: 8 | G117: 0
A118: 25 | B118: S+T+P | C118: 8 | D118: M | E118: 8 | G118: 0
A119: 32 | B119: S+T+P | C119: 8 | D119: M | E119: 8 | G119: 0
A120: 40 | B120: S+T+P | C120: 8 | D120: M | E120: 8 | G120: 0
A121: 50 | B121: S+T+P | C121: 8 | D121: M | E121: 8 | G121: 0
...

Sheet Suivi actualisation
A1: SUIVI DES VERSIONS
A2: Version | B2: Date V | C2: Objet
A3: V99 | B3: 46296 | C3: maquette de test
